codenerix_extensions/__init__.py
codenerix_extensions/helpers.py
codenerix_extensions/validators.py
codenerix_extensions/views.py
codenerix_extensions/files/__init__.py
codenerix_extensions/files/models.py
codenerix_extensions/files/views.py
codenerix_extensions/files/__pycache__/__init__.cpython-310.pyc
codenerix_extensions/files/__pycache__/__init__.cpython-311.pyc
codenerix_extensions/files/__pycache__/__init__.cpython-35.pyc
codenerix_extensions/files/__pycache__/__init__.cpython-38.pyc
codenerix_extensions/files/__pycache__/__init__.cpython-39.pyc
codenerix_extensions/files/__pycache__/models.cpython-310.pyc
codenerix_extensions/files/__pycache__/models.cpython-311.pyc
codenerix_extensions/files/__pycache__/models.cpython-35.pyc
codenerix_extensions/files/__pycache__/models.cpython-38.pyc
codenerix_extensions/files/__pycache__/models.cpython-39.pyc
codenerix_extensions/files/__pycache__/views.cpython-310.pyc
codenerix_extensions/files/__pycache__/views.cpython-311.pyc
codenerix_extensions/files/__pycache__/views.cpython-35.pyc
codenerix_extensions/files/__pycache__/views.cpython-38.pyc
codenerix_extensions/files/__pycache__/views.cpython-39.pyc
codenerix_extensions/lib/__init__.py
codenerix_extensions/lib/cryptography.py
codenerix_extensions/lib/.ropeproject/config.py
codenerix_extensions/lib/.ropeproject/globalnames
codenerix_extensions/lib/.ropeproject/history
codenerix_extensions/lib/.ropeproject/objectdb
codenerix_extensions/lib/__pycache__/__init__.cpython-310.pyc
codenerix_extensions/lib/__pycache__/__init__.cpython-35.pyc
codenerix_extensions/lib/__pycache__/__init__.cpython-39.pyc
codenerix_extensions/lib/__pycache__/cryptography.cpython-310.pyc
codenerix_extensions/lib/__pycache__/cryptography.cpython-35.pyc
codenerix_extensions/lib/__pycache__/cryptography.cpython-39.pyc
codenerix_extensions/locale/en/LC_MESSAGES/django.po
codenerix_extensions/locale/es/LC_MESSAGES/django.mo
codenerix_extensions/locale/es/LC_MESSAGES/django.po
django_codenerix_extensions-4.0.4.dist-info/LICENSE
django_codenerix_extensions-4.0.4.dist-info/METADATA
django_codenerix_extensions-4.0.4.dist-info/WHEEL
django_codenerix_extensions-4.0.4.dist-info/top_level.txt
django_codenerix_extensions-4.0.4.dist-info/RECORD
